prettierprint.py
prettierprint-1.1.2.dist-info/LICENSE
prettierprint-1.1.2.dist-info/METADATA
prettierprint-1.1.2.dist-info/WHEEL
prettierprint-1.1.2.dist-info/top_level.txt
prettierprint-1.1.2.dist-info/RECORD
