Metadata-Version: 2.1
Name: prettierprint
Version: 1.1.2
Summary: Python module for clean, human-readable printing of data structures.
Author-email: Jordan Nimlos <jordan.nimlos@gmail.com>
License: MIT License        
Project-URL: Homepage, https://github.com/nimjor/prettierprint
Keywords: print,pprint,prettier,prettyprint,cleanprint
Classifier: License :: OSI Approved :: MIT License
Classifier: Programming Language :: Python
Classifier: Programming Language :: Python :: 3
Requires-Python: >=3
License-File: LICENSE
